ltn/__init__.py
ltn/core.py
ltn/fuzzy_ops.py
ltn/utils.py
ltn-2.1.dist-info/LICENSE
ltn-2.1.dist-info/METADATA
ltn-2.1.dist-info/WHEEL
ltn-2.1.dist-info/top_level.txt
ltn-2.1.dist-info/RECORD
