Metadata-Version: 2.1
Name: ltn
Version: 2.1
Summary: Logic Tensor Networks
Author-email: Samy Badreddine <badreddine.samy@gmail.com>
Project-URL: Homepage, https://github.com/logictensornetworks/logictensornetworks
Project-URL: Issue Tracker, https://github.com/logictensornetworks/logictensornetworks/issues
Keywords: machine-learning,framework,neural-symbolic-computing,fuzzy-logic,tensorflow
Classifier: Development Status :: 5 - Production/Stable
Classifier: Programming Language :: Python :: 3.7
Classifier: Programming Language :: Python :: 3.8
Classifier: Programming Language :: Python :: 3.9
Classifier: Topic :: Scientific/Engineering :: Artificial Intelligence
Classifier: License :: OSI Approved :: MIT License
Requires-Python: >=3.7
License-File: LICENSE
Requires-Dist: numpy
Requires-Dist: tensorflow ; sys_platform != "darwin" or platform_machine != "arm64"
Requires-Dist: tensorflow-macos ; sys_platform == "darwin" and platform_machine == "arm64"
